secp256k1Crypto/__init__.py
secp256k1Crypto/__main__.py
secp256k1Crypto-0.0.1.dist-info/LICENSE
secp256k1Crypto-0.0.1.dist-info/METADATA
secp256k1Crypto-0.0.1.dist-info/WHEEL
secp256k1Crypto-0.0.1.dist-info/top_level.txt
secp256k1Crypto-0.0.1.dist-info/RECORD
