Metadata-Version: 2.1
Name: secp256k1Crypto
Version: 0.0.1
Summary: Multi OS supported secp256k1-py
Home-page: https://github.com/hoorin/secp256k1-py-multi-os
Author: HooriRn
Author-email: HooriRn@protonmail.com
License: MIT
Keywords: secp256k1,secp256k1-py,crypto
Platform: UNKNOWN
Classifier: Intended Audience :: Developers
Classifier: Topic :: Software Development :: Libraries :: Python Modules
Classifier: License :: OSI Approved :: MIT License
Classifier: Programming Language :: Python :: 3
Classifier: Programming Language :: Python :: 3.6
Classifier: Programming Language :: Python :: 3.7
Classifier: Programming Language :: Python
License-File: LICENSE
Requires-Dist: electrumsv-secp256k1 (>=0.9.3)
